{
    "type": "botania:petal_apothecary",
    "ingredients": [
      {
        "item": "nyagibits_bytes:botania_schematic"
      },
      {
        "item": "botania:manasteel_sword"
      },
      {
        "item": "botania:manasteel_axe"
      },
      {
        "item": "botania:manasteel_pick"
      },
      {
        "item": "botania:manasteel_shovel"
      },
      {
        "item": "botania:manasteel_hoe"
      },
      {
        "item": "aiotbotania:livingrock_aiot"
      }
    ],
    "output": {
      "item": "aiotbotania:manasteel_aiot"
    },
    "reagent": {
      "tag": "botania:seed_apothecary_reagent"
    }
  }