{
    "type":"immersiveengineering:mineral_mix",
    "dimensions":
        [
            "minecraft:overworld"
        ],
    "fail_chance":0.5,
    "ores":
        [
            {
                "chance":0.2,
                "output":
                    {
                        "item":"nyagibits_bytes:raw_columbite"
                    }
                },
            {
                "chance":0.4,
                "output":
                    {
                        "item":"nyagibits_bytes:raw_fluorspar"
                    }
                },
            {
                "chance":0.1,
                "output":
                    {
                        "item":"nyagibits_bytes:raw_phosphorite"
                    }
                },
            {
                "chance":0.3,
                "output":
                    {
                        "item":"nyagibits_bytes:raw_zirconia"
                    }
                }
        ],
    "spoils":
        [
            {
                "chance":0.1,
                "output":
                    {
                        "item":"minecraft:basalt"
                    }
                }
        ],
    "weight":14
}